fasttest_selenium/__init__.py
fasttest_selenium/driver.py
fasttest_selenium/project.py
fasttest_selenium/common/__init__.py
fasttest_selenium/common/check.py
fasttest_selenium/common/debug.py
fasttest_selenium/common/decorator.py
fasttest_selenium/common/dict.py
fasttest_selenium/common/logging.py
fasttest_selenium/common/variable_global.py
fasttest_selenium/drivers/__init__.py
fasttest_selenium/drivers/driver.py
fasttest_selenium/drivers/driver_base.py
fasttest_selenium/keywords/__init__.py
fasttest_selenium/keywords/keywords.py
fasttest_selenium/result/__init__.py
fasttest_selenium/result/html_result.py
fasttest_selenium/result/test_result.py
fasttest_selenium/result/test_runner.py
fasttest_selenium/result/resource/css.css
fasttest_selenium/result/resource/js.js
fasttest_selenium/runner/__init__.py
fasttest_selenium/runner/action_analysis.py
fasttest_selenium/runner/action_executor.py
fasttest_selenium/runner/case_analysis.py
fasttest_selenium/runner/run_case.py
fasttest_selenium/runner/test_case.py
fasttest_selenium/utils/__init__.py
fasttest_selenium/utils/opcv_utils.py
fasttest_selenium/utils/server_utils.py
fasttest_selenium/utils/testcast_utils.py
fasttest_selenium/utils/yaml_utils.py
fasttest_selenium-0.1.6.dist-info/LICENSE
fasttest_selenium-0.1.6.dist-info/METADATA
fasttest_selenium-0.1.6.dist-info/WHEEL
fasttest_selenium-0.1.6.dist-info/top_level.txt
fasttest_selenium-0.1.6.dist-info/RECORD
