Metadata-Version: 2.1
Name: fasttest-selenium
Version: 0.1.6
Summary: WEB自动化快速编写工具
Home-page: https://github.com/Jodeee/fasttest_selenium
Author: IMJIE
Author-email: imjie@outlook.com
License: UNKNOWN
Keywords: selenium,WEB自动化,关键字驱动
Platform: UNKNOWN
Classifier: Programming Language :: Python :: 3
Classifier: License :: OSI Approved :: MIT License
Requires-Python: >=3.6
